json_yaml_schema_converter/__init__.py
json_yaml_schema_converter/cli.py
json_yaml_schema_converter/converter.py
json_yaml_schema_converter-0.6.0.dist-info/licenses/LICENSE
json_yaml_schema_converter-0.6.0.dist-info/METADATA
json_yaml_schema_converter-0.6.0.dist-info/WHEEL
json_yaml_schema_converter-0.6.0.dist-info/entry_points.txt
json_yaml_schema_converter-0.6.0.dist-info/top_level.txt
json_yaml_schema_converter-0.6.0.dist-info/RECORD
