Metadata-Version: 2.4
Name: json_yaml_schema_converter
Version: 0.6.0
Summary: Convert JSON API responses to YAML schema
Home-page: https://github.com/revan-more/json_yaml_schema_converter
Author: Revan More
Author-email: revanmore12@gmail.com
Project-URL: Bug Reports, https://github.com/revan-more/json_yaml_schema_converter/issues
Project-URL: Source, https://github.com/revan-more/json_yaml_schema_converter
Project-URL: Documentation, https://github.com/revan-more/json_yaml_schema_converter#readme
Keywords: json yaml schema converter api openapi swagger
Classifier: Development Status :: 4 - Beta
Classifier: Intended Audience :: Developers
Classifier: Topic :: Software Development :: Libraries :: Python Modules
Classifier: Topic :: Text Processing :: Markup
Classifier: Topic :: Utilities
Classifier: License :: OSI Approved :: MIT License
Classifier: Programming Language :: Python :: 3
Classifier: Programming Language :: Python :: 3.7
Classifier: Programming Language :: Python :: 3.8
Classifier: Programming Language :: Python :: 3.9
Classifier: Programming Language :: Python :: 3.10
Classifier: Programming Language :: Python :: 3.11
Classifier: Operating System :: OS Independent
Requires-Python: >=3.7
License-File: LICENSE
Requires-Dist: PyYAML>=6.0
Requires-Dist: setuptools
Requires-Dist: wheel
Requires-Dist: twine
Dynamic: author
Dynamic: author-email
Dynamic: classifier
Dynamic: description
Dynamic: description-content-type
Dynamic: home-page
Dynamic: keywords
Dynamic: license-file
Dynamic: project-url
Dynamic: requires-dist
Dynamic: requires-python
Dynamic: summary
